build/lib/gitto/__init__.py
gitto/__init__.py
gitto-0.0.2.dist-info/LICENSE
gitto-0.0.2.dist-info/METADATA
gitto-0.0.2.dist-info/WHEEL
gitto-0.0.2.dist-info/entry_points.txt
gitto-0.0.2.dist-info/top_level.txt
gitto-0.0.2.dist-info/RECORD
