Metadata-Version: 2.1
Name: gitto
Version: 0.0.2
Summary: Automate commits to github
Home-page: https://github.com/FedeClaudi/gitto
Author: Federico Claudi
License: UNKNOWN
Platform: UNKNOWN
Requires-Python: >=3.6,
Requires-Dist: rich (>=9.0.0)
Requires-Dist: click
Provides-Extra: dev
Requires-Dist: coverage-badge ; extra == 'dev'
